README.rst
setup.py
historylink/__init__.py
historylink/manager.py
historylink/middleware.py
historylink/models.py
historylink.egg-info/PKG-INFO
historylink.egg-info/SOURCES.txt
historylink.egg-info/dependency_links.txt
historylink.egg-info/top_level.txt
historylink.egg-info/zip-safe
historylink/management/__init__.py
historylink/management/commands/__init__.py
historylink/management/commands/historylink_sync.py