Metadata-Version: 1.0
Name: historylink
Version: 0.0.1
Summary: Store model url change, od a permanent redirect on 404
Home-page: https://github.com/oxys-net/django-historylink
Author: Oxys
Author-email: UNKNOWN
License: UNKNOWN
Keywords: django url change redirect 404 301
Platform: UNKNOWN
Classifier: Intended Audience :: Developers
Classifier: Natural Language :: English
Classifier: Operating System :: OS Independent
Classifier: Programming Language :: Python
